apptranslate/__init__.py
apptranslate/translate.py
apptranslate-0.1.1.dist-info/LICENSE
apptranslate-0.1.1.dist-info/METADATA
apptranslate-0.1.1.dist-info/WHEEL
apptranslate-0.1.1.dist-info/entry_points.txt
apptranslate-0.1.1.dist-info/top_level.txt
apptranslate-0.1.1.dist-info/RECORD
