Metadata-Version: 2.1
Name: apptranslate
Version: 0.1.1
Summary: Android App Translator v2
Home-page: https://github.com/gr8mawiya
Author: Mawiya
Author-email: mawiya@outlook.be
Classifier: Programming Language :: Python :: 3
Classifier: License :: OSI Approved :: MIT License
Classifier: Operating System :: OS Independent
Requires-Python: >=3.8
License-File: LICENSE
Requires-Dist: googletrans
